pytrends/__init__.py
pytrends/dailydata.py
pytrends/exceptions.py
pytrends/request.py
pytrends/test_trendReq.py
kpytrends-4.7.4.dist-info/LICENSE
kpytrends-4.7.4.dist-info/METADATA
kpytrends-4.7.4.dist-info/WHEEL
kpytrends-4.7.4.dist-info/top_level.txt
kpytrends-4.7.4.dist-info/RECORD
