Metadata-Version: 2.1
Name: kpytrends
Version: 4.7.4
Summary: Pseudo API for Google Trends
Home-page: https://github.com/kkristof200/pytrends
Author: ['John Hogue', 'Burton DeWilde']
Author-email: dreyco676@gmail.com
License: Apache 2.0
Keywords: google trends api search
Platform: UNKNOWN
Classifier: Development Status :: 4 - Beta
Classifier: Intended Audience :: Developers
Classifier: Programming Language :: Python :: 2.7
Classifier: Programming Language :: Python :: 3.3
Classifier: Programming Language :: Python :: 3.4
Classifier: Programming Language :: Python :: 3.5
Classifier: Programming Language :: Python :: 3.6
Classifier: Programming Language :: Python :: 3.7
Classifier: License :: OSI Approved :: MIT License
Requires-Dist: pandas
Requires-Dist: requests
